{
  "id": 1776537190028,
  "isim": "MELTEM ŞENER",
  "not": "",
  "arsiv": false,
  "haftalar": [
    {
      "haftaNo": 1,
      "baslangic": "2026-04-12",
      "bitis": "2026-04-18",
      "aciklama": "",
      "pdf": null,
      "pdfName": null,
      "pdfOrijinalIsim": null,
      "pdfYolu": null,
      "githubUrl": null,
      "indirmeUrl": null,
      "kayitTarihi": null,
      "tarifKartlar": [],
      "tarifler": [],
      "gptMesaj": "",
      "kilitli": false
    }
  ],
  "olusturmaTarihi": "2026-04-18T18:33:10.028Z",
  "yeniSistem": true,
  "sonGuncelleme": "2026-04-18T18:33:26.734Z",
  "githubKaydedildi": true
}